pyflexconfig.py
pyflexconfig-1.0.0.data/data/VERSION.txt
pyflexconfig-1.0.0.dist-info/LICENSE.txt
pyflexconfig-1.0.0.dist-info/METADATA
pyflexconfig-1.0.0.dist-info/WHEEL
pyflexconfig-1.0.0.dist-info/top_level.txt
pyflexconfig-1.0.0.dist-info/RECORD
