Metadata-Version: 2.1
Name: pyflexconfig
Version: 1.0.0
Summary: A simple Python app configuration file helper
Home-page: https://github.com/glenfant/pyflexconfig
Author: Gilles Lenfant
Author-email: gilles.lenfant@gmail.com
License: MIT
Keywords: Configuration,Settings
Platform: any
Classifier: Programming Language :: Python :: 3 :: Only
Classifier: Programming Language :: Python :: 3.6
Classifier: Programming Language :: Python :: 3.7
Classifier: Programming Language :: Python :: 3.8
Classifier: Programming Language :: Python :: Implementation :: CPython
Classifier: License :: OSI Approved :: MIT License
Classifier: Development Status :: 4 - Beta
Classifier: Operating System :: OS Independent
Classifier: Intended Audience :: Developers
Classifier: Topic :: Software Development :: Libraries
Requires-Python: >=3.6
Requires-Dist: python-dotenv
Provides-Extra: dev
Requires-Dist: pytest ; extra == 'dev'
